pybecker/__init__.py
pybecker/__main__.py
pybecker/becker.py
pybecker/becker_helper.py
pybecker/database.py
pybecker-1.1.0.dist-info/AUTHORS
pybecker-1.1.0.dist-info/LICENSE
pybecker-1.1.0.dist-info/METADATA
pybecker-1.1.0.dist-info/WHEEL
pybecker-1.1.0.dist-info/top_level.txt
pybecker-1.1.0.dist-info/RECORD
