Metadata-Version: 2.1
Name: pybecker
Version: 1.1.0
Summary: pybecker is a library to control becker RF shutters
Home-page: https://github.com/nicolasberthel/pybecker
Author: Nicolas Berthel
Author-email: contact@nicolasberthel.fr
License: UNKNOWN
Platform: UNKNOWN
Classifier: Programming Language :: Python
Classifier: Development Status :: 5 - Production/Stable
Classifier: Natural Language :: English
Classifier: Environment :: Console
Classifier: Intended Audience :: Developers
Classifier: License :: OSI Approved :: MIT License
Classifier: Operating System :: OS Independent
Classifier: Topic :: Software Development :: Libraries :: Python Modules
Classifier: Topic :: System :: Hardware :: Hardware Drivers
Classifier: Topic :: Home Automation
License-File: LICENSE
License-File: AUTHORS
Requires-Dist: pyserial (>=3.4)
